py_simple_trees/__init__.py
py_simple_trees/node.py
py_simple_trees/tree.py
py_simple_trees-0.1.3.dist-info/LICENSE
py_simple_trees-0.1.3.dist-info/METADATA
py_simple_trees-0.1.3.dist-info/WHEEL
py_simple_trees-0.1.3.dist-info/RECORD
