Metadata-Version: 2.1
Name: py-simple-trees
Version: 0.1.3
Summary: 
Author: lpthong90
Author-email: lpthong90@gmail.com
Requires-Python: >=3.9,<4.0
Classifier: Programming Language :: Python :: 3
Classifier: Programming Language :: Python :: 3.9
Classifier: Programming Language :: Python :: 3.10
Classifier: Programming Language :: Python :: 3.11
Classifier: Programming Language :: Python :: 3.12
